CHANGES.txt
LICENSE.txt
MANIFEST.in
README.rst
setup.py
js/__init__.py
js.uuid.egg-info/PKG-INFO
js.uuid.egg-info/SOURCES.txt
js.uuid.egg-info/dependency_links.txt
js.uuid.egg-info/entry_points.txt
js.uuid.egg-info/namespace_packages.txt
js.uuid.egg-info/not-zip-safe
js.uuid.egg-info/requires.txt
js.uuid.egg-info/top_level.txt
js/uuid/__init__.py
js/uuid/test_uuid.txt
js/uuid/resources/uuid.js