Metadata-Version: 1.1
Name: js.uuid
Version: 1.4.7
Summary: Fanstatic packaging of node-uuid
Home-page: https://github.com/minddistrict/js.uuid
Author: UNKNOWN
Author-email: UNKNOWN
License: MIT
Platform: UNKNOWN
Classifier: Programming Language :: Python :: 2.6
Classifier: Programming Language :: Python :: 2.7
Classifier: Programming Language :: Python :: 3.2
Classifier: Programming Language :: Python :: Implementation :: PyPy
